nbconvert_article_html/__init__.py
nbconvert_article_html/template/article-html/conf.json
nbconvert_article_html/template/article-html/index.html.j2
nbconvert_article_html-0.9.1.dist-info/LICENSE
nbconvert_article_html-0.9.1.dist-info/METADATA
nbconvert_article_html-0.9.1.dist-info/WHEEL
nbconvert_article_html-0.9.1.dist-info/entry_points.txt
nbconvert_article_html-0.9.1.dist-info/top_level.txt
nbconvert_article_html-0.9.1.dist-info/RECORD
