Metadata-Version: 2.1
Name: nbconvert-article-html
Version: 0.9.1
Summary: Tools based on nbconvert to render a Jupyter notebook into a self-contained HTML file whose layout is similar to a LaTeX article.
Home-page: https://github.com/hamelin/nbconvert-article-html
Author: Benoit Hamelin
Author-email: benoit@benoithamelin.com
Classifier: Development Status :: 3 - Alpha
Classifier: Intended Audience :: Developers
Classifier: License :: OSI Approved :: MIT License
Classifier: Programming Language :: Python :: 3
Classifier: Topic :: Software Development :: Interpreters
Requires-Python: >=3.8
License-File: LICENSE
Requires-Dist: nbconvert
Requires-Dist: bs4
